riyadhai_blingfire/__init__.py
riyadhai_blingfire-1.0.0.dist-info/licenses/LICENSE
riyadhai_blingfire-1.0.0.dist-info/licenses/NOTICE
riyadhai_blingfire-1.0.0.dist-info/METADATA
riyadhai_blingfire-1.0.0.dist-info/WHEEL
riyadhai_blingfire-1.0.0.dist-info/top_level.txt
riyadhai_blingfire-1.0.0.dist-info/RECORD
