Metadata-Version: 2.4
Name: riyadhai-blingfire
Version: 1.0.0
Summary: Optional accelerator package for RiyadhAI SDK tokenization.
Author: RiyadhAI LLC
License: Apache License
Requires-Python: <3.14,>=3.10
License-File: LICENSE
License-File: NOTICE
Requires-Dist: riyadhai>=1.3.14
Dynamic: license-file
